async_task/__init__.py
async_task/async_task.py
simple_async_task-1.0.4.dist-info/LICENSE
simple_async_task-1.0.4.dist-info/METADATA
simple_async_task-1.0.4.dist-info/WHEEL
simple_async_task-1.0.4.dist-info/top_level.txt
simple_async_task-1.0.4.dist-info/RECORD
