Metadata-Version: 2.1
Name: simple-async-task
Version: 1.0.4
Summary: A simple library for managing asynchrony.
Author-email: Matt Fowler <mattefowler@gmail.com>
License:                                  Apache License
Keywords: threading,async
Classifier: Programming Language :: Python :: 3 :: Only
Classifier: Programming Language :: Python :: 3.11
Classifier: Topic :: Software Development :: Libraries :: Python Modules
Requires-Python: >=3.11
License-File: LICENSE
